AUTHORS.md
LICENSE.md
MANIFEST.in
README.md
setup.py
django_password_strength_sk/__init__.py
django_password_strength_sk/tests.py
django_password_strength_sk/widgets.py
django_password_strength_sk.egg-info/PKG-INFO
django_password_strength_sk.egg-info/SOURCES.txt
django_password_strength_sk.egg-info/dependency_links.txt
django_password_strength_sk.egg-info/not-zip-safe
django_password_strength_sk.egg-info/top_level.txt
django_password_strength_sk/static/django_password_strength_sk/js/password_strength.js
django_password_strength_sk/static/django_password_strength_sk/js/zxcvbn-async.js
django_password_strength_sk/static/django_password_strength_sk/js/zxcvbn.js