Metadata-Version: 1.1
Name: django-password-strength-sk
Version: 1.2.1
Summary: This package contains an extention of the Django password widget including a password strength meter and crack time powered by zxcvbn.
Home-page: http://thegoods.aj7may.com/django-password-strength
Author: A.J. May
Author-email: ivan6258@gmail.com
License: BSD
Keywords: password meter zxcvbn strength security django
Platform: UNKNOWN
Classifier: Development Status :: 5 - Production/Stable
Classifier: Environment :: Web Environment
Classifier: Framework :: Django
Classifier: Intended Audience :: Developers
Classifier: License :: OSI Approved :: BSD License
Classifier: Operating System :: OS Independent
Classifier: Programming Language :: Python
Classifier: Programming Language :: Python :: 2
Classifier: Programming Language :: Python :: 2.7
Classifier: Topic :: Internet :: WWW/HTTP
